fastgedcom/__init__.py
fastgedcom/base.py
fastgedcom/family_link.py
fastgedcom/helpers.py
fastgedcom/parser.py
fastgedcom/py.typed
fastgedcom-1.1.4.dist-info/licenses/LICENSE
fastgedcom-1.1.4.dist-info/METADATA
fastgedcom-1.1.4.dist-info/WHEEL
fastgedcom-1.1.4.dist-info/top_level.txt
fastgedcom-1.1.4.dist-info/RECORD
