Metadata-Version: 2.4
Name: fastgedcom
Version: 1.1.4
Summary: A lightweight tool to easily parse, browse and edit gedcom files.
Author-email: Gatien Bouyer <gatien.bouyer.dev@gmail.com>
License-Expression: MIT
Project-URL: Bug Tracker, https://github.com/GatienBouyer/fastgedcom/issues
Project-URL: Source, https://github.com/GatienBouyer/fastgedcom
Project-URL: Documentation, https://fastgedcom.readthedocs.io/en/latest/
Keywords: fastgedcom,gedcom,parser,genealogy
Classifier: Programming Language :: Python :: 3.10
Classifier: Programming Language :: Python :: 3.11
Classifier: Programming Language :: Python :: 3.12
Classifier: Programming Language :: Python :: 3.13
Classifier: Programming Language :: Python :: 3.14
Classifier: Topic :: Sociology :: Genealogy
Classifier: Intended Audience :: Developers
Classifier: Operating System :: OS Independent
Classifier: Development Status :: 5 - Production/Stable
Requires-Python: >=3.10
License-File: LICENSE
Provides-Extra: dev
Requires-Dist: mypy; extra == "dev"
Requires-Dist: isort; extra == "dev"
Requires-Dist: autopep8; extra == "dev"
Requires-Dist: build; extra == "dev"
Requires-Dist: twine; extra == "dev"
Requires-Dist: sphinx-rtd-theme; extra == "dev"
Requires-Dist: sphinx-autoapi; extra == "dev"
Provides-Extra: ansel
Requires-Dist: ansel>=1.0.0; extra == "ansel"
Dynamic: license-file
